{
  "slug": "coffee-table-with-planter",
  "title": "Coffee Table with Planter",
  "summary": "This DIY coffee table is made out of 3/4\" plywood and coated with cement.",
  "description": "This DIY coffee table is made out of 3/4\" plywood and coated with cement. There is a hole in the top that allows a plant to grow through.",
  "category": "outdoor",
  "difficulty": 2,
  "timeMinMinutes": 120,
  "timeMaxMinutes": 225,
  "timeLabel": "2–3.8 hours",
  "costTier": "TIER_2",
  "costMinCents": 4800,
  "costMaxCents": 8000,
  "tags": [
    "Outdoor Living",
    "Beginner"
  ],
  "tools": [
    {
      "slug": "pocket-hole-jig",
      "essential": true
    },
    {
      "slug": "circular-saw",
      "essential": true
    },
    {
      "slug": "jigsaw",
      "essential": true
    },
    {
      "slug": "drill-driver",
      "essential": true
    },
    {
      "slug": "random-orbit-sander",
      "essential": true
    }
  ],
  "materials": [
    {
      "name": "Sheet of sanded pine plywood, 4'x8'x3/4\"",
      "unit": "board",
      "quantity": 1
    },
    {
      "name": "Box Of 1 1/4\" Pocket-Hole Screws (See Tools List)",
      "unit": "each",
      "quantity": 1
    },
    {
      "name": "Sandpaper, various grits",
      "unit": "each",
      "quantity": 1
    },
    {
      "name": "Bag of feather finish concrete mix",
      "unit": "each",
      "quantity": 1
    },
    {
      "name": "Drywall sanding mesh",
      "unit": "each",
      "quantity": 1
    }
  ],
  "cutList": [],
  "steps": [
    {
      "title": "Cut the plywood",
      "body": "Cut the pieces of the table according to the cut list and diagram shown here.",
      "image": "https://pub-b845b7e7b4924e4d8f2520661b54734d.r2.dev/plans/61bc69ea3a50c702.webp"
    },
    {
      "title": "Cut a hole in the top",
      "body": "Draw a 10\" diameter circle on one end of the top board and use a jigsaw to cut it out.",
      "image": "https://pub-b845b7e7b4924e4d8f2520661b54734d.r2.dev/plans/7790a8657708528b.webp"
    },
    {
      "title": "Assemble, measure, and cut",
      "body": "Use pocket holes to attach the two long sides to the top. Take a measurement between the sides and cut pieces to fit on the ends. Use pocket holes to attach the pieces.",
      "image": "https://pub-b845b7e7b4924e4d8f2520661b54734d.r2.dev/plans/8408e26fc4d43deb.webp"
    },
    {
      "title": "Add feet",
      "body": "Screw 6\" wide pieces that extend past the bottom of the box by 3/4\" with 1-1/4\" finish screws.",
      "image": "https://pub-b845b7e7b4924e4d8f2520661b54734d.r2.dev/plans/30964cc0a91e1d5e.webp"
    },
    {
      "title": "Cover in concrete",
      "body": "Mix feather finish cement mix and coat the exterior of the plywood box."
    }
  ],
  "images": [
    {
      "url": "https://pub-b845b7e7b4924e4d8f2520661b54734d.r2.dev/plans/81c95ebd42e736fb.webp",
      "alt": "Coffee Table with Planter",
      "isPrimary": true
    },
    {
      "url": "https://pub-b845b7e7b4924e4d8f2520661b54734d.r2.dev/plans/e99ca86f00e36887.webp",
      "alt": "Coffee Table with Planter — step photo 1",
      "isPrimary": false
    },
    {
      "url": "https://pub-b845b7e7b4924e4d8f2520661b54734d.r2.dev/plans/3355582e27e7ef1e.webp",
      "alt": "Coffee Table with Planter — step photo 2",
      "isPrimary": false
    },
    {
      "url": "https://pub-b845b7e7b4924e4d8f2520661b54734d.r2.dev/plans/61bc69ea3a50c702.webp",
      "alt": "Coffee Table with Planter — step photo 3",
      "isPrimary": false
    },
    {
      "url": "https://pub-b845b7e7b4924e4d8f2520661b54734d.r2.dev/plans/7790a8657708528b.webp",
      "alt": "Coffee Table with Planter — step photo 4",
      "isPrimary": false
    },
    {
      "url": "https://pub-b845b7e7b4924e4d8f2520661b54734d.r2.dev/plans/8408e26fc4d43deb.webp",
      "alt": "Coffee Table with Planter — step photo 5",
      "isPrimary": false
    },
    {
      "url": "https://pub-b845b7e7b4924e4d8f2520661b54734d.r2.dev/plans/30964cc0a91e1d5e.webp",
      "alt": "Coffee Table with Planter — step photo 6",
      "isPrimary": false
    }
  ],
  "published": true
}
