{
  "slug": "recycling-sorting-bin",
  "title": "Recycling Sorting Bin",
  "summary": "Make it easy to keep your recyclables separated with this recycling bin.",
  "description": "Make it easy to keep your recyclables separated with this recycling bin. It holds three 23-gallon plastic trash bins that can easily be removed, and houses them in a handsome wood cabinet. The center is made from 1×4, 1×6, and 2×2 boards, and it goes together with pocket-hole screws and nails.",
  "category": "storage",
  "difficulty": 2,
  "timeMinMinutes": 255,
  "timeMaxMinutes": 495,
  "timeLabel": "4.3–8.3 hours",
  "costTier": "TIER_3",
  "costMinCents": 12400,
  "costMaxCents": 20700,
  "tags": [
    "Garage",
    "Beginner"
  ],
  "tools": [
    {
      "slug": "miter-saw",
      "essential": true
    },
    {
      "slug": "combination-square",
      "essential": false
    },
    {
      "slug": "tape-measure",
      "essential": false
    },
    {
      "slug": "brad-nailer",
      "essential": true
    },
    {
      "slug": "drill-driver",
      "essential": true
    },
    {
      "slug": "pocket-hole-jig",
      "essential": true
    },
    {
      "slug": "random-orbit-sander",
      "essential": true
    }
  ],
  "materials": [
    {
      "name": "Board, 1x4 96\"",
      "unit": "board",
      "quantity": 3
    },
    {
      "name": "Board, 1x4 48\"",
      "unit": "board",
      "quantity": 1
    },
    {
      "name": "Board, 1x6 96\"",
      "unit": "board",
      "quantity": 9
    },
    {
      "name": "Board, 2x2 96\"",
      "unit": "board",
      "quantity": 5
    },
    {
      "name": "23-Gallon Plastic Trash Can",
      "unit": "each",
      "quantity": 3
    },
    {
      "name": "2 1/2\" coarse-thread pocket-hole screws",
      "unit": "each",
      "quantity": 40
    },
    {
      "name": "1 1/4\" coarse-thread pocket-hole screws",
      "unit": "each",
      "quantity": 46
    },
    {
      "name": "1-1/4\" brad nails",
      "unit": "each",
      "quantity": 116
    },
    {
      "name": "Wood glue",
      "unit": "each",
      "quantity": 1
    }
  ],
  "cutList": [
    {
      "part": "Leg",
      "quantity": 4,
      "thicknessIn": 1,
      "widthIn": 1,
      "lengthIn": 33
    },
    {
      "part": "Long Frame Rail",
      "quantity": 4,
      "thicknessIn": 1,
      "widthIn": 1,
      "lengthIn": 37
    },
    {
      "part": "Short Frame Rail",
      "quantity": 4,
      "thicknessIn": 1,
      "widthIn": 1,
      "lengthIn": 22
    },
    {
      "part": "Divider Rail",
      "quantity": 2,
      "thicknessIn": 1,
      "widthIn": 1,
      "lengthIn": 22
    },
    {
      "part": "Base Slats",
      "quantity": 6,
      "thicknessIn": 0.75,
      "widthIn": 5,
      "lengthIn": 25
    },
    {
      "part": "Short Side Slats",
      "quantity": 6,
      "thicknessIn": 0.75,
      "widthIn": 5,
      "lengthIn": 25
    },
    {
      "part": "Long Side Slats",
      "quantity": 4,
      "thicknessIn": 0.75,
      "widthIn": 5,
      "lengthIn": 27
    },
    {
      "part": "Short Front/Back Slats",
      "quantity": 4,
      "thicknessIn": 0.75,
      "widthIn": 5,
      "lengthIn": 40
    },
    {
      "part": "Long Front/Back Slats",
      "quantity": 6,
      "thicknessIn": 0.75,
      "widthIn": 5,
      "lengthIn": 41
    },
    {
      "part": "Long Lid Rail",
      "quantity": 2,
      "thicknessIn": 0.75,
      "widthIn": 3,
      "lengthIn": 42
    },
    {
      "part": "Short Lid Rail",
      "quantity": 4,
      "thicknessIn": 0.75,
      "widthIn": 3,
      "lengthIn": 20
    },
    {
      "part": "Lid Front/Back Rail",
      "quantity": 2,
      "thicknessIn": 0.75,
      "widthIn": 3,
      "lengthIn": 42
    },
    {
      "part": "Lid Side Rail",
      "quantity": 2,
      "thicknessIn": 0.75,
      "widthIn": 3,
      "lengthIn": 26
    }
  ],
  "steps": [
    {
      "title": "Make the Base Frame Parts",
      "body": "Cut four Legs, Four Long Frame Rails, four Short Frame Rails, and two Divider Rails to length from 2x2 pine boards, as shown as shown in the cutting diagram. Set your pocket-hole jig for 1 1/2\" material and drill holes into the Long Frame Rails, the Short Frame Rails, and the Divider Rails at the locations shown.",
      "image": "https://pub-b845b7e7b4924e4d8f2520661b54734d.r2.dev/plans/e5aaab1530661301.webp"
    },
    {
      "title": "Assemble the Front and Back Frames",
      "body": "Lay out two Long Frame Rails with two Legs, as shown, so that the upper Long Frame Rail is flush with the upper ends of the Legs, and the lower Long Frame Rail is positioned 1 1/4\" up from the lower ends of the Legs. Make sure pocket screws are facing downward. Spread glue on the ends of the Long Frame Rails, and then attach them to the Legs using 2 1/2\" coarse-thread pocket-hole screws. Repeat this process to put together the second frame assembly.",
      "image": "https://pub-b845b7e7b4924e4d8f2520661b54734d.r2.dev/plans/ecaee0d1366ac6b1.webp"
    },
    {
      "title": "Connect the Front and Back Frames",
      "body": "Connect the four Frame Short Rails to the first side assembly, aligning them with the Long Frame Rails, and attach the Short Frame Rails using glue and 2 1/2\" coarse-thread pocket-hole screws. Then set the second side assembly in place and secure it to the Short Frame Rails in the same manner.",
      "image": "https://pub-b845b7e7b4924e4d8f2520661b54734d.r2.dev/plans/ae479284870da8a7.webp"
    },
    {
      "title": "Attach the Divider Rails",
      "body": "You can now add the two Divider Rails to strengthen the base assembly, and to help keep the trash bins separated in the recycling center. Position the Divider Rails between the upper Long Frame Rails, as shown, so that they are spaced evenly. Then attach the Divider Rails using glue and 2 1/2\" coarse-thread pocket-hole screws, as shown.",
      "image": "https://pub-b845b7e7b4924e4d8f2520661b54734d.r2.dev/plans/bd8db9c1624e6fff.webp"
    },
    {
      "title": "Cut and Attach Base Slats",
      "body": "Cut six Base Slats to length from 1x6 pine boards, as shown in the cutting diagram. Notice that the boards are placed in pairs, and that the gaps between the pairs are larger. Attach the Base Slats using glue and 1 1/2\" brad nails—about three brads per board end. You can use a hammer and nails for this, but a brad nailer works best. If you don’t have one, you have a couple choices: You can rent an 18-gauge brad nailer and a compressor at a local tool rental shop, or you can buy a nailer. Prices are pretty low these days, and it’s a very handy tool to have around. You’ll find nailer/compressor combos, and even cordless, battery-operated nailers.",
      "image": "https://pub-b845b7e7b4924e4d8f2520661b54734d.r2.dev/plans/eb25bc93b45d7384.webp"
    },
    {
      "title": "Attach the First Side Slats",
      "body": "Cut six Short Side Slats, four Long Side Slats, four Short Front/Back Slats and six Long Front/Back Slats, as shown in the cutting diagram. Using scrap 2x2 pieces as spacers, set the first Short Side Slats on the spacers, and position the Slat so the ends are flush with the outsides of the Legs. Next, using wood glue and 1 1/2\" brad nails attach the first two Short Side Slats to the Frame Legs—we used four nails at each end to attach these Slats.",
      "image": "https://pub-b845b7e7b4924e4d8f2520661b54734d.r2.dev/plans/96a44bc49607a383.webp"
    },
    {
      "title": "Attach the First Front/Back Slats",
      "body": "Using the same 2x2 spacers, set the first Long Front/Back Slats in position so that the ends are flush with the Short Side Slats. Secure these Long Front/Back Slats to the Legs using wood glue and 1 1/2\" brad nails, as shown.",
      "image": "https://pub-b845b7e7b4924e4d8f2520661b54734d.r2.dev/plans/ceabd607d512d15d.webp"
    },
    {
      "title": "Attach the Remaining Base Slats",
      "body": "Now you can attach the remaining slats to the base. Use 1/4\"-thick spacers, as shown, to space the slats properly.",
      "image": "https://pub-b845b7e7b4924e4d8f2520661b54734d.r2.dev/plans/b4c708f75ce8f79c.webp"
    },
    {
      "title": "Make the Lid Parts",
      "body": "Note: the Lid for the recycling center is sized slightly larger than the base so it will slide on and off the frame easily. Cut two Long Lid Rails, four Short Lid Rails, two Lid Front/Back Rails, and two Lid End Rails to length from 1x4 boards, as shown in the cutting diagram. Set your pocket-hole jig for 3/4\"-thick material, and then drill pocket holes in the parts at the locations shown. Note that the Long Lid Rails don’t get any pocket holes.",
      "image": "https://pub-b845b7e7b4924e4d8f2520661b54734d.r2.dev/plans/dbc591a1f2567e07.webp"
    },
    {
      "title": "Assemble the Lid Frame",
      "body": "Attach one Long Lid Rail to four Short Lid Rails using glue and 1 1/4\" coarse-thread pocket-hole screws, as shown. Next, set the second Long Lid Rail in position and secure it to the Short Lid Rails in the same way.",
      "image": "https://pub-b845b7e7b4924e4d8f2520661b54734d.r2.dev/plans/7c90b735b6d8e63b.webp"
    },
    {
      "title": "Complete the Lid",
      "body": "Attach the one Lid Front/Back Rail to the lid frame assembly using glue and 1 1/4\" coarse-thread pocket-hole screws, as shown. Then add the Lid End Rails, and then the final Lid Front/Back Rail",
      "image": "https://pub-b845b7e7b4924e4d8f2520661b54734d.r2.dev/plans/96d24b9708bdf5e3.webp"
    },
    {
      "title": "Add a Protective Finish",
      "body": "With assembly done, you could slip your trash bins into the recycling center and put it to work without any stain or finish. Over time, though, the wood will get dirty and dingy looking. So, we decided to dress ours up a bit. First, we gave the exterior a light sanding with 120-grit sandpaper. Then we brushed a quick coat of polyurethane onto the outside of the base assembly. For the lid, we used a dark stain, and then painted three panels using chalkboard paint. Once dry, we wrote the items that get placed in each bin onto the chalkboard panels. Then we slipped the trash bins into place and put the recycling center to work in the garage."
    }
  ],
  "images": [
    {
      "url": "https://pub-b845b7e7b4924e4d8f2520661b54734d.r2.dev/plans/bfe8ba8b804f3e24.webp",
      "alt": "Recycling Sorting Bin",
      "isPrimary": true
    },
    {
      "url": "https://pub-b845b7e7b4924e4d8f2520661b54734d.r2.dev/plans/f10b3923bfd9a8ac.webp",
      "alt": "Recycling Sorting Bin — step photo 1",
      "isPrimary": false
    },
    {
      "url": "https://pub-b845b7e7b4924e4d8f2520661b54734d.r2.dev/plans/0ac1162fa197520f.webp",
      "alt": "Recycling Sorting Bin — step photo 2",
      "isPrimary": false
    },
    {
      "url": "https://pub-b845b7e7b4924e4d8f2520661b54734d.r2.dev/plans/4823b7c267c4385a.webp",
      "alt": "Recycling Sorting Bin — step photo 3",
      "isPrimary": false
    },
    {
      "url": "https://pub-b845b7e7b4924e4d8f2520661b54734d.r2.dev/plans/2c72b77eb49df693.webp",
      "alt": "Recycling Sorting Bin — step photo 4",
      "isPrimary": false
    },
    {
      "url": "https://pub-b845b7e7b4924e4d8f2520661b54734d.r2.dev/plans/e5aaab1530661301.webp",
      "alt": "Recycling Sorting Bin — step photo 5",
      "isPrimary": false
    },
    {
      "url": "https://pub-b845b7e7b4924e4d8f2520661b54734d.r2.dev/plans/ecaee0d1366ac6b1.webp",
      "alt": "Recycling Sorting Bin — step photo 6",
      "isPrimary": false
    },
    {
      "url": "https://pub-b845b7e7b4924e4d8f2520661b54734d.r2.dev/plans/ae479284870da8a7.webp",
      "alt": "Recycling Sorting Bin — step photo 7",
      "isPrimary": false
    },
    {
      "url": "https://pub-b845b7e7b4924e4d8f2520661b54734d.r2.dev/plans/bd8db9c1624e6fff.webp",
      "alt": "Recycling Sorting Bin — step photo 8",
      "isPrimary": false
    },
    {
      "url": "https://pub-b845b7e7b4924e4d8f2520661b54734d.r2.dev/plans/eb25bc93b45d7384.webp",
      "alt": "Recycling Sorting Bin — step photo 9",
      "isPrimary": false
    },
    {
      "url": "https://pub-b845b7e7b4924e4d8f2520661b54734d.r2.dev/plans/96a44bc49607a383.webp",
      "alt": "Recycling Sorting Bin — step photo 10",
      "isPrimary": false
    },
    {
      "url": "https://pub-b845b7e7b4924e4d8f2520661b54734d.r2.dev/plans/ceabd607d512d15d.webp",
      "alt": "Recycling Sorting Bin — step photo 11",
      "isPrimary": false
    },
    {
      "url": "https://pub-b845b7e7b4924e4d8f2520661b54734d.r2.dev/plans/b4c708f75ce8f79c.webp",
      "alt": "Recycling Sorting Bin — step photo 12",
      "isPrimary": false
    },
    {
      "url": "https://pub-b845b7e7b4924e4d8f2520661b54734d.r2.dev/plans/dbc591a1f2567e07.webp",
      "alt": "Recycling Sorting Bin — step photo 13",
      "isPrimary": false
    },
    {
      "url": "https://pub-b845b7e7b4924e4d8f2520661b54734d.r2.dev/plans/7c90b735b6d8e63b.webp",
      "alt": "Recycling Sorting Bin — step photo 14",
      "isPrimary": false
    },
    {
      "url": "https://pub-b845b7e7b4924e4d8f2520661b54734d.r2.dev/plans/96d24b9708bdf5e3.webp",
      "alt": "Recycling Sorting Bin — step photo 15",
      "isPrimary": false
    }
  ],
  "published": true
}
